BCD_7.v
module BCD(clk, rst_syn, load_syn, Din);
input clk;
input rst_syn;
input load_syn;
input [3:0] Din;
output [3:0] Q_out;
reg [3:0] Q_out;
output [7:0] Ans;
reg [7:0] Ans;
initial
begin
    Q_out[3:0]  = 4'b0000;
end

always@ (posedge clk)
begin 
    if (!rst_syn)
        Q_out=4'b0000;
    else if (load_syn)
        Q_out=Din;
    else if (Q_out == 9)
        Q_out = 0;
    else 
        Q_out = Q_out +1;
end 

always @(Q_out)
case (Q_out)
    4'b0000:
        Ans=8'b11000000;
    4'b0001:
        Ans=8'b11111001;
    4'b0010:
        Ans=8'b10100100;
    4'b0011:
        Ans=8'b10110000;
    4'b0100:
        Ans=8'b10011001;
    4'b0101:
        Ans=8'b10010010;
    4'b0110:
        Ans=8'b10000010;
    4'b0111:
        Ans=8'b11111000;
    4'b1000:
        Ans=8'b10000000;
    4'b1001:
        Ans=8'b10010000;
    4'b1010:
        Ans=8'b10100000;
    4'b1011:
        Ans=8'b10000011;
    4'b1100:
        Ans=8'b10100111;
    4'b1101:
        Ans=8'b10100001;
    4'b1110:
        Ans=8'b10000100;
    4'b1111:
        Ans=8'b11110001;
    default:
        Ans=8'b10000100;
endcase
endmodule

BCD_7_tb.v
module BCD_7_tb();
reg clk_tb, reset_tb, load_tb;
reg[3:0] Din_tb;
BCD BCD_1(.clk(clk_tb), .rst_syn(reset_tb), .load_syn(load_tb), .Din(Din_tb));
initial
begin 
    clk_tb=1'b1;
    reset_tb= 1'b1;
    load_tb= 1'b0;
    Din_tb=4'b0101;
end

always 
begin 
    #10 clk_tb = ~clk_tb;
end 

initial
begin 

    #80 reset_tb = 1'b0;
    #10 reset_tb = 1'b1;
end 

initial
begin 

    #80 load_tb = 1'b1;
    #10 load_tb = 1'b0;
end 

initial
begin 

    #120 load_tb = 1'b1;
    #10 load_tb = 1'b0;
end 

initial
begin 

    #400 $finish;
end 

initial
begin 
    $dumpfile("BCD_To_7.vcd");
    $dumpvars(0,BCD_1);
end 
endmodule

BCD_To_7.vcd
$date
	Fri May 06 01:04:02 2022
$end
$version
	Icarus Verilog
$end
$timescale
	1s
$end
$scope module BCD_7_tb $end
$scope module BCD_1 $end
$var wire 4 ! Din [3:0] $end
$var wire 1 " clk $end
$var wire 1 # load_syn $end
$var wire 1 $ rst_syn $end
$var reg 8 % Ans [7:0] $end
$var reg 4 & Q_out [3:0] $end
$upscope $end
$upscope $end
$enddefinitions $end
#0
$dumpvars
b1 &
b11111001 %
1$
0#
1"
b101 !
$end
#10
0"
#20
b10100100 %
b10 &
1"
#30
0"
#40
b10110000 %
b11 &
1"
#50
0"
#60
b10011001 %
b100 &
1"
#70
0"
#80
b11000000 %
b0 &
1"
1#
0$
#90
0"
0#
1$
#100
b11111001 %
b1 &
1"
#110
0"
#120
b10010010 %
b101 &
1"
1#
#130
0"
0#
#140
b10000010 %
b110 &
1"
#150
0"
#160
b11111000 %
b111 &
1"
#170
0"
#180
b10000000 %
b1000 &
1"
#190
0"
#200
b10010000 %
b1001 &
1"
#210
0"
#220
b11000000 %
b0 &
1"
#230
0"
#240
b11111001 %
b1 &
1"
#250
0"
#260
b10100100 %
b10 &
1"
#270
0"
#280
b10110000 %
b11 &
1"
#290
0"
#300
b10011001 %
b100 &
1"
#310
0"
#320
b10010010 %
b101 &
1"
#330
0"
#340
b10000010 %
b110 &
1"
#350
0"
#360
b11111000 %
b111 &
1"
#370
0"
#380
b10000000 %
b1000 &
1"
#390
0"
#400
b10010000 %
b1001 &
1"
